roamkit/marko/fenced_divs/__init__.py
roamkit_marko_fenced_divs-1.0.0.dist-info/licenses/LICENSE
roamkit_marko_fenced_divs-1.0.0.dist-info/WHEEL
roamkit_marko_fenced_divs-1.0.0.dist-info/METADATA
roamkit_marko_fenced_divs-1.0.0.dist-info/RECORD
