Metadata-Version: 2.4
Name: roamkit-marko-fenced-divs
Version: 1.0.0
Summary: Fenced divs extension for Marko
Keywords: markdown marko fenced
Author: Kevin Wetzels
Author-email: Kevin Wetzels <kevin@roam.be>
License-Expression: MIT
License-File: LICENSE
Classifier: Development Status :: 3 - Alpha
Classifier: Intended Audience :: Developers
Classifier: Natural Language :: English
Classifier: Programming Language :: Python :: 3 :: Only
Classifier: Programming Language :: Python :: 3.9
Classifier: Programming Language :: Python :: 3.10
Classifier: Programming Language :: Python :: 3.11
Classifier: Programming Language :: Python :: 3.12
Classifier: Programming Language :: Python :: 3.13
Classifier: Programming Language :: Python :: 3.14
Classifier: Typing :: Typed
Requires-Dist: marko>=2.2.0
Maintainer: Kevin Wetzels
Maintainer-email: Kevin Wetzels <kevin@roam.be>
Requires-Python: >=3.9
Project-URL: Repository, https://github.com/roam/roamkit-marko-fenced-divs
